{
  "updated_at": "2026-06-25T11:30:13.781204+00:00",
  "items": [
    {
      "title": "Dolphin Emulator Progress Release 2606",
      "summary": "Sujet technologique en tendance. Résumé IA indisponible temporairement.",
      "source": "Flux RSS"
    },
    {
      "title": "Aisle Discovers 6 New CVEs in Curl, Including the Oldest Issue Ever Reported",
      "summary": "Sujet technologique en tendance. Résumé IA indisponible temporairement.",
      "source": "Flux RSS"
    },
    {
      "title": "Wikipedia Workers in Britain set global first by seeking union recognition",
      "summary": "Sujet technologique en tendance. Résumé IA indisponible temporairement.",
      "source": "Flux RSS"
    },
    {
      "title": "Half-Life 2 in a Browser",
      "summary": "Sujet technologique en tendance. Résumé IA indisponible temporairement.",
      "source": "Flux RSS"
    },
    {
      "title": "Medical students are using popular research tool to pump out misleading studies",
      "summary": "Sujet technologique en tendance. Résumé IA indisponible temporairement.",
      "source": "Flux RSS"
    },
    {
      "title": "Cloudflare launched self-managed OAuth for all",
      "summary": "Sujet technologique en tendance. Résumé IA indisponible temporairement.",
      "source": "Flux RSS"
    },
    {
      "title": "Zombie unicorns are haunting Silicon Valley",
      "summary": "Sujet technologique en tendance. Résumé IA indisponible temporairement.",
      "source": "Flux RSS"
    },
    {
      "title": "Mixing Visual and Textual Code",
      "summary": "Sujet technologique en tendance. Résumé IA indisponible temporairement.",
      "source": "Flux RSS"
    },
    {
      "title": "LuaJIT 3.0 proposed syntax extensions",
      "summary": "Sujet technologique en tendance. Résumé IA indisponible temporairement.",
      "source": "Flux RSS"
    },
    {
      "title": "Blogging can just be stating the obvious",
      "summary": "Sujet technologique en tendance. Résumé IA indisponible temporairement.",
      "source": "Flux RSS"
    }
  ]
}