{
  "updated_at": "2026-07-03T01:26:57.315868+00:00",
  "items": [
    {
      "title": "\"An AI Job Apocalypse?\" – Goldman Sachs Report [pdf]",
      "summary": "Sujet technologique en tendance. Résumé IA indisponible temporairement.",
      "source": "Flux RSS"
    },
    {
      "title": "GitHub is proud to announce that you can now obtain your public repo on CD-ROM",
      "summary": "Sujet technologique en tendance. Résumé IA indisponible temporairement.",
      "source": "Flux RSS"
    },
    {
      "title": "An American Privacy Emergency",
      "summary": "Sujet technologique en tendance. Résumé IA indisponible temporairement.",
      "source": "Flux RSS"
    },
    {
      "title": "Right to Local Intelligence",
      "summary": "Sujet technologique en tendance. Résumé IA indisponible temporairement.",
      "source": "Flux RSS"
    },
    {
      "title": "crustc: entirety of `rustc`, translated to C",
      "summary": "Sujet technologique en tendance. Résumé IA indisponible temporairement.",
      "source": "Flux RSS"
    },
    {
      "title": "Mystery identity of 'Green Boots' climber is finally solved after DNA test",
      "summary": "Sujet technologique en tendance. Résumé IA indisponible temporairement.",
      "source": "Flux RSS"
    },
    {
      "title": "Virginia bans sale of geolocation data",
      "summary": "Sujet technologique en tendance. Résumé IA indisponible temporairement.",
      "source": "Flux RSS"
    },
    {
      "title": "Lightning Memory-Mapped Database Manager (LMDB) 1.0",
      "summary": "Sujet technologique en tendance. Résumé IA indisponible temporairement.",
      "source": "Flux RSS"
    },
    {
      "title": "Great Salt Lake Tracker – Grow the Flow",
      "summary": "Sujet technologique en tendance. Résumé IA indisponible temporairement.",
      "source": "Flux RSS"
    },
    {
      "title": "EFF letter to FTC on X consent order (2 July 2026) [pdf]",
      "summary": "Sujet technologique en tendance. Résumé IA indisponible temporairement.",
      "source": "Flux RSS"
    }
  ]
}